<?xml version="1.0"?>
<catalogue>

    <message key="Contact us">Kontaktieren Sie uns</message>
    <message key="Company">Firma</message>
    <message key="Name">Name</message>
    <message key="First Name">Vorname</message>
    <message key="Last Name">Name</message>
    <message key="Street Address">Adresse</message>
    <message key="Zip Code">PLZ</message>
    <message key="City">Ort</message>
    <message key="Country">Land</message>
    <message key="E-mail Address">E-Mail-Adresse</message>
    <message key="Phone">Telefon</message>

    <message key="Comments">Kommentar</message>
    <message key="Please get in contact with us">Bitte kontaktieren sie mich</message>
    <message key="Please send me your Portfolio and your Checklists">Bitte senden sie mir ihre Dokumentation und Checklisten</message>

    <message key="Submit">Senden</message>
	<message key="This field is required, please complete it.">Dieses Feld ist erforderlich.</message>    
<message key="This field is has to be checked.">Dieses Feld ist erforderlich.</message>
<message key="This field is required, please check it.">Dieses Feld ist erforderlich. Bitte ankreuzen.</message>
</catalogue>
